[
  {
    "$schema": "https://logicstamp.dev/schemas/context/v0.1.json",
    "position": "1/3",
    "type": "LogicStampBundle",
    "schemaVersion": "0.1",
    "entryId": "components/flashcard/flashcard.stories.tsx",
    "depth": 2,
    "createdAt": "2025-12-22T18:06:43.043Z",
    "bundleHash": "uifb:88ab172624fb3d131c4a7f54",
    "graph": {
      "nodes": [
        {
          "entryId": "components/flashcard/flashcard.stories.tsx",
          "contract": {
            "type": "UIFContract",
            "schemaVersion": "0.3",
            "kind": "react:component",
            "entryId": "components/flashcard/flashcard.stories.tsx",
            "description": "flashcard.stories - Card display component",
            "version": {
              "variables": ["DEFAULT_DETAILS", "Default", "meta"],
              "hooks": [],
              "components": [
                "Flashcard",
                "FlashcardAdditionalData",
                "FlashcardDetailsLabel",
                "FlashcardDetailsList",
                "FlashcardDetailsValue",
                "FlashcardHero",
                "Fragment"
              ],
              "functions": [],
              "imports": [
                ".",
                "@accelint/core",
                "@storybook/react-vite",
                "react/jsx-runtime"
              ]
            },
            "logicSignature": {
              "props": {},
              "emits": {}
            },
            "exports": "named",
            "semanticHash": "uif:1e8ab18b72af27f67f110cfe",
            "fileHash": "uif:818d70e5b4e947c189437d84"
          },
          "codeHeader": null,
          "code": "/*\n * Copyright 2025 Hypergiant Galactic Systems Inc. All rights reserved.\n * This file is licensed to you under the Apache License, Version 2.0 (the \"License\");\n * you may not use this file except in compliance with the License. You may obtain a copy\n * of the License at https://www.apache.org/licenses/LICENSE-2.0\n *\n * Unless required by applicable law or agreed to in writing, software distributed under\n * the License is distributed on an \"AS IS\" BASIS, WITHOUT WARRANTIES OR REPRESENTATIONS\n * OF ANY KIND, either express or implied. See the License for the specific language\n * governing permissions and limitations under the License.\n */\n\nimport { uuid } from '@accelint/core';\nimport { Fragment } from 'react/jsx-runtime';\nimport {\n  Flashcard,\n  FlashcardAdditionalData,\n  FlashcardDetailsLabel,\n  FlashcardDetailsList,\n  FlashcardDetailsValue,\n  FlashcardHero,\n} from '.';\nimport type { Meta, StoryObj } from '@storybook/react-vite';\n\nconst DEFAULT_DETAILS = [\n  { label: 'key', value: 'value-1', id: uuid() },\n  { label: 'key', value: 'value-2', id: uuid() },\n  { label: 'key', value: 'value-3', id: uuid() },\n  { label: 'key', value: 'value-4', id: uuid() },\n  { label: 'key', value: 'value-5', id: uuid() },\n  { label: 'key', value: 'value-6', id: uuid() },\n  { label: 'key', value: 'value-7', id: uuid() },\n];\n\nconst meta = {\n  title: 'Components/Flashcard',\n  component: Flashcard,\n  args: {\n    isLoading: false,\n    header: 'IDENTIFIER',\n    subheader: 'DATA',\n  },\n} satisfies Meta<typeof Flashcard>;\n\nexport default meta;\ntype Story = StoryObj<typeof meta>;\nexport const Default: Story = {\n  render: (args) => {\n    return (\n      <Flashcard {...args}>\n        <FlashcardHero />\n        <FlashcardAdditionalData>SECONDARY_DATA_01</FlashcardAdditionalData>\n        <FlashcardAdditionalData>SECONDARY_DATA_02</FlashcardAdditionalData>\n        <FlashcardDetailsList data-testid='secondary'>\n          {DEFAULT_DETAILS.map((detail) => (\n            <Fragment key={detail.id}>\n              <FlashcardDetailsLabel>{detail.label}</FlashcardDetailsLabel>\n              <FlashcardDetailsValue>{detail.value}</FlashcardDetailsValue>\n            </Fragment>\n          ))}\n        </FlashcardDetailsList>\n      </Flashcard>\n    );\n  },\n};\n"
        }
      ],
      "edges": []
    },
    "meta": {
      "missing": [
        {
          "name": "Flashcard",
          "reason": "No contract found (third-party or not scanned)",
          "referencedBy": "components/flashcard/flashcard.stories.tsx"
        },
        {
          "name": "FlashcardAdditionalData",
          "reason": "No contract found (third-party or not scanned)",
          "referencedBy": "components/flashcard/flashcard.stories.tsx"
        },
        {
          "name": "FlashcardDetailsLabel",
          "reason": "No contract found (third-party or not scanned)",
          "referencedBy": "components/flashcard/flashcard.stories.tsx"
        },
        {
          "name": "FlashcardDetailsList",
          "reason": "No contract found (third-party or not scanned)",
          "referencedBy": "components/flashcard/flashcard.stories.tsx"
        },
        {
          "name": "FlashcardDetailsValue",
          "reason": "No contract found (third-party or not scanned)",
          "referencedBy": "components/flashcard/flashcard.stories.tsx"
        },
        {
          "name": "FlashcardHero",
          "reason": "No contract found (third-party or not scanned)",
          "referencedBy": "components/flashcard/flashcard.stories.tsx"
        },
        {
          "name": "Fragment",
          "reason": "No contract found (third-party or not scanned)",
          "referencedBy": "components/flashcard/flashcard.stories.tsx"
        }
      ],
      "source": "logicstamp-context@0.3.2"
    }
  },
  {
    "$schema": "https://logicstamp.dev/schemas/context/v0.1.json",
    "position": "2/3",
    "type": "LogicStampBundle",
    "schemaVersion": "0.1",
    "entryId": "components/flashcard/index.tsx",
    "depth": 2,
    "createdAt": "2025-12-22T18:06:43.062Z",
    "bundleHash": "uifb:97d9b67673329a294d81c64e",
    "graph": {
      "nodes": [
        {
          "entryId": "components/flashcard/index.tsx",
          "contract": {
            "type": "UIFContract",
            "schemaVersion": "0.3",
            "kind": "react:component",
            "entryId": "components/flashcard/index.tsx",
            "description": "index - Presentational component",
            "version": {
              "variables": [
                "FlashcardContext",
                "FlashcardHeader",
                "FlashcardSubheader"
              ],
              "hooks": ["useContext"],
              "components": [
                "DetailsList",
                "DetailsListLabel",
                "DetailsListValue",
                "FlashcardContext.Provider",
                "FlashcardHeader",
                "FlashcardSubheader",
                "Skeleton"
              ],
              "functions": [
                "Flashcard",
                "FlashcardAdditionalData",
                "FlashcardDetailsLabel",
                "FlashcardDetailsList",
                "FlashcardDetailsValue",
                "FlashcardHero"
              ],
              "imports": [
                "../details-list",
                "../details-list/label",
                "../details-list/value",
                "../skeleton",
                "./styles.module.css",
                "./types",
                "@accelint/design-foundation/lib/utils",
                "client-only",
                "react",
                "react-aria-components"
              ]
            },
            "logicSignature": {
              "props": {},
              "emits": {}
            },
            "exports": {
              "named": [
                "Flashcard",
                "FlashcardAdditionalData",
                "FlashcardContext",
                "FlashcardDetailsLabel",
                "FlashcardDetailsList",
                "FlashcardDetailsValue",
                "FlashcardHero"
              ]
            },
            "prediction": ["Consumes React Context for shared state"],
            "style": {
              "styleSources": {
                "cssModule": "./styles.module.css",
                "cssDetails": {
                  "selectors": [
                    ".container",
                    ".data",
                    ".details-label",
                    ".details-list",
                    ".details-value",
                    ".half",
                    ".header",
                    ".hero",
                    ".skeleton",
                    ".smaller",
                    ".subheader"
                  ],
                  "properties": ["min-width"]
                }
              }
            },
            "semanticHash": "uif:c4d9c9dc5735b259cd658c17",
            "fileHash": "uif:4f7096c150a9ac4ce7faaad8"
          },
          "codeHeader": null,
          "code": "/*\n * Copyright 2025 Hypergiant Galactic Systems Inc. All rights reserved.\n * This file is licensed to you under the Apache License, Version 2.0 (the \"License\");\n * you may not use this file except in compliance with the License. You may obtain a copy\n * of the License at https://www.apache.org/licenses/LICENSE-2.0\n *\n * Unless required by applicable law or agreed to in writing, software distributed under\n * the License is distributed on an \"AS IS\" BASIS, WITHOUT WARRANTIES OR REPRESENTATIONS\n * OF ANY KIND, either express or implied. See the License for the specific language\n * governing permissions and limitations under the License.\n */\n\n'use client';\nimport { clsx } from '@accelint/design-foundation/lib/utils';\nimport 'client-only';\nimport { createContext, useContext } from 'react';\nimport { Heading, Text } from 'react-aria-components';\nimport { DetailsList } from '../details-list';\nimport { DetailsListLabel } from '../details-list/label';\nimport { DetailsListValue } from '../details-list/value';\nimport { Skeleton } from '../skeleton';\nimport styles from './styles.module.css';\nimport type {\n  FlashcardComponentProps,\n  FlashcardDetailsListProps,\n  FlashcardProps,\n} from './types';\n\nexport const FlashcardContext = createContext<FlashcardProps>({\n  isLoading: false,\n  header: '',\n  subheader: '',\n});\n\n/**\n * Example usage.\n *\n * ```tsx\n * <Flashcard isLoading={isLoading} header=\"Identifier\" subheader=\"DATA\">\n *  <FlashcardHero />\n *  <FlashcardAdditionalData>\n *    {secondaryData}\n *  </FlashcardAdditionalData>\n *  <FlashcardDetailsList>\n *    {detail.map((detail) => (\n *     <Fragment key={detail.id}>\n *       <FlashcardDetailsLabel>\n *         {detail.label}\n *       </FlashcardDetailsLabel>\n *       <FlashcardDetailsValue>\n *         {detail.value}\n *       </FlashcardDetailsValue>\n *     </Fragment>\n *     ))}\n *  </FlashcardDetailsList>\n * </Flashcard>\n * ```\n */\nexport function Flashcard(props: FlashcardProps) {\n  const { isLoading, header, subheader, children, className, ...rest } = props;\n\n  return (\n    <FlashcardContext.Provider value={{ isLoading, header, subheader }}>\n      <div {...rest} className={clsx(styles.container, className)}>\n        {children}\n      </div>\n    </FlashcardContext.Provider>\n  );\n}\nFlashcard.displayName = 'Flashcard';\n\nexport function FlashcardHero(props: FlashcardComponentProps) {\n  const { children, className, ...rest } = props;\n  const { isLoading, header, subheader } = useContext(FlashcardContext);\n\n  if (isLoading) {\n    return (\n      <div {...rest} className={clsx(styles.hero, className, 'gap-s')}>\n        <Skeleton className={styles.skeleton} data-testid='hero-skeleton' />\n        <Skeleton className={clsx(styles.skeleton, styles.half)} />\n      </div>\n    );\n  }\n\n  return (\n    <div {...rest} className={clsx(styles.hero, className)}>\n      <FlashcardHeader className={styles.header}>{header}</FlashcardHeader>\n      <FlashcardSubheader className={styles.subheader}>\n        {subheader}\n      </FlashcardSubheader>\n    </div>\n  );\n}\nFlashcardHero.displayName = 'FlashcardHero';\n\nconst FlashcardHeader = Heading;\nconst FlashcardSubheader = Text;\n\nexport function FlashcardAdditionalData(props: FlashcardComponentProps) {\n  const { children, className, ...rest } = props;\n  const { isLoading } = useContext(FlashcardContext);\n\n  // While loading, don't display.\n  if (isLoading) {\n    return null;\n  }\n\n  return (\n    <div {...rest} className={clsx(styles.data, className)}>\n      {children}\n    </div>\n  );\n}\nFlashcardAdditionalData.displayName = 'FlashcardAdditionalData';\n\nexport function FlashcardDetailsList(props: FlashcardDetailsListProps) {\n  const { children, className, ...rest } = props;\n  return (\n    <DetailsList\n      {...rest}\n      align='justify'\n      classNames={{ list: clsx(styles['details-list'], className) }}\n    >\n      {children}\n    </DetailsList>\n  );\n}\nFlashcardDetailsList.displayName = 'FlashcardDetailsList';\n\nexport function FlashcardDetailsLabel(props: FlashcardComponentProps) {\n  const { isLoading } = useContext(FlashcardContext);\n  const { className, children, ...rest } = props;\n  return (\n    <DetailsListLabel\n      {...rest}\n      className={clsx(styles['details-label'], className)}\n    >\n      {isLoading ? (\n        <Skeleton className={clsx(styles.skeleton, styles.smaller)} />\n      ) : (\n        children\n      )}\n    </DetailsListLabel>\n  );\n}\nFlashcardDetailsLabel.displayName = 'FlashcardDetailsLabel';\n\nexport function FlashcardDetailsValue(props: FlashcardComponentProps) {\n  const { isLoading } = useContext(FlashcardContext);\n  const { className, children, ...rest } = props;\n  return (\n    <DetailsListValue\n      {...rest}\n      className={clsx(styles['details-value'], className)}\n    >\n      {isLoading ? (\n        <Skeleton className={clsx(styles.skeleton, styles.smaller)} />\n      ) : (\n        children\n      )}\n    </DetailsListValue>\n  );\n}\nFlashcardDetailsValue.displayName = 'FlashcardDetailsValue';\n"
        }
      ],
      "edges": []
    },
    "meta": {
      "missing": [
        {
          "name": "DetailsList",
          "reason": "No contract found (third-party or not scanned)",
          "referencedBy": "components/flashcard/index.tsx"
        },
        {
          "name": "DetailsListLabel",
          "reason": "No contract found (third-party or not scanned)",
          "referencedBy": "components/flashcard/index.tsx"
        },
        {
          "name": "DetailsListValue",
          "reason": "No contract found (third-party or not scanned)",
          "referencedBy": "components/flashcard/index.tsx"
        },
        {
          "name": "FlashcardContext.Provider",
          "reason": "No contract found (third-party or not scanned)",
          "referencedBy": "components/flashcard/index.tsx"
        },
        {
          "name": "FlashcardHeader",
          "reason": "No contract found (third-party or not scanned)",
          "referencedBy": "components/flashcard/index.tsx"
        },
        {
          "name": "FlashcardSubheader",
          "reason": "No contract found (third-party or not scanned)",
          "referencedBy": "components/flashcard/index.tsx"
        },
        {
          "name": "Skeleton",
          "reason": "No contract found (third-party or not scanned)",
          "referencedBy": "components/flashcard/index.tsx"
        }
      ],
      "source": "logicstamp-context@0.3.2"
    }
  },
  {
    "$schema": "https://logicstamp.dev/schemas/context/v0.1.json",
    "position": "3/3",
    "type": "LogicStampBundle",
    "schemaVersion": "0.1",
    "entryId": "components/flashcard/types.ts",
    "depth": 2,
    "createdAt": "2025-12-22T18:06:43.062Z",
    "bundleHash": "uifb:778d58e79f6bcff8288b7922",
    "graph": {
      "nodes": [
        {
          "entryId": "components/flashcard/types.ts",
          "contract": {
            "type": "UIFContract",
            "schemaVersion": "0.3",
            "kind": "ts:module",
            "entryId": "components/flashcard/types.ts",
            "description": "types - Type definitions",
            "version": {
              "variables": [],
              "hooks": [],
              "components": [],
              "functions": [],
              "imports": ["../details-list/types", "react"]
            },
            "logicSignature": {
              "props": {
                "children": {
                  "type": "React.ReactNode",
                  "optional": true
                },
                "ref": {
                  "type": "React.Ref<HTMLDivElement> & React.Ref<HTMLDListElement>",
                  "optional": true
                },
                "key": {
                  "type": "React.Key",
                  "optional": true
                },
                "defaultChecked": {
                  "type": "boolean",
                  "optional": true
                },
                "defaultValue": {
                  "type": "string | number | readonly string[]",
                  "optional": true
                },
                "suppressContentEditableWarning": {
                  "type": "boolean",
                  "optional": true
                },
                "suppressHydrationWarning": {
                  "type": "boolean",
                  "optional": true
                },
                "accessKey": {
                  "type": "string",
                  "optional": true
                },
                "autoCapitalize": {
                  "type": "\"off\" | \"none\" | \"on\" | \"sentences\" | \"words\" | \"characters\" | (string & {})",
                  "optional": true
                },
                "autoFocus": {
                  "type": "boolean",
                  "optional": true
                },
                "className": {
                  "type": "string",
                  "optional": true
                },
                "contentEditable": {
                  "type": "Booleanish | \"inherit\" | \"plaintext-only\"",
                  "optional": true
                },
                "contextMenu": {
                  "type": "string",
                  "optional": true
                },
                "dir": {
                  "type": "string",
                  "optional": true
                },
                "draggable": {
                  "type": "Booleanish",
                  "optional": true
                },
                "enterKeyHint": {
                  "type": "literal-union",
                  "literals": [
                    "search",
                    "enter",
                    "done",
                    "go",
                    "next",
                    "previous",
                    "send"
                  ],
                  "optional": true
                },
                "hidden": {
                  "type": "boolean",
                  "optional": true
                },
                "id": {
                  "type": "string",
                  "optional": true
                },
                "lang": {
                  "type": "string",
                  "optional": true
                },
                "nonce": {
                  "type": "string",
                  "optional": true
                },
                "slot": {
                  "type": "string",
                  "optional": true
                },
                "spellCheck": {
                  "type": "Booleanish",
                  "optional": true
                },
                "style": {
                  "type": "React.CSSProperties",
                  "optional": true
                },
                "tabIndex": {
                  "type": "number",
                  "optional": true
                },
                "title": {
                  "type": "string",
                  "optional": true
                },
                "translate": {
                  "type": "literal-union",
                  "literals": ["yes", "no"],
                  "optional": true
                },
                "radioGroup": {
                  "type": "string",
                  "optional": true
                },
                "role": {
                  "type": "React.AriaRole",
                  "optional": true
                },
                "about": {
                  "type": "string",
                  "optional": true
                },
                "content": {
                  "type": "string",
                  "optional": true
                },
                "datatype": {
                  "type": "string",
                  "optional": true
                },
                "inlist": {
                  "type": "any",
                  "optional": true
                },
                "prefix": {
                  "type": "string",
                  "optional": true
                },
                "property": {
                  "type": "string",
                  "optional": true
                },
                "rel": {
                  "type": "string",
                  "optional": true
                },
                "resource": {
                  "type": "string",
                  "optional": true
                },
                "rev": {
                  "type": "string",
                  "optional": true
                },
                "typeof": {
                  "type": "string",
                  "optional": true
                },
                "vocab": {
                  "type": "string",
                  "optional": true
                },
                "autoCorrect": {
                  "type": "string",
                  "optional": true
                },
                "autoSave": {
                  "type": "string",
                  "optional": true
                },
                "color": {
                  "type": "string",
                  "optional": true
                },
                "itemProp": {
                  "type": "string",
                  "optional": true
                },
                "itemScope": {
                  "type": "boolean",
                  "optional": true
                },
                "itemType": {
                  "type": "string",
                  "optional": true
                },
                "itemID": {
                  "type": "string",
                  "optional": true
                },
                "itemRef": {
                  "type": "string",
                  "optional": true
                },
                "results": {
                  "type": "number",
                  "optional": true
                },
                "security": {
                  "type": "string",
                  "optional": true
                },
                "unselectable": {
                  "type": "literal-union",
                  "literals": ["off", "on"],
                  "optional": true
                },
                "popover": {
                  "type": "\"\" | \"auto\" | \"manual\" | \"hint\"",
                  "optional": true
                },
                "popoverTargetAction": {
                  "type": "literal-union",
                  "literals": ["toggle", "show", "hide"],
                  "optional": true
                },
                "popoverTarget": {
                  "type": "string",
                  "optional": true
                },
                "inert": {
                  "type": "boolean",
                  "optional": true
                },
                "inputMode": {
                  "type": "literal-union",
                  "literals": [
                    "search",
                    "text",
                    "none",
                    "tel",
                    "url",
                    "email",
                    "numeric",
                    "decimal"
                  ],
                  "optional": true
                },
                "is": {
                  "type": "string",
                  "optional": true
                },
                "exportparts": {
                  "type": "string",
                  "optional": true
                },
                "part": {
                  "type": "string",
                  "optional": true
                },
                "aria-activedescendant": {
                  "type": "string",
                  "optional": true
                },
                "aria-atomic": {
                  "type": "Booleanish",
                  "optional": true
                },
                "aria-autocomplete": {
                  "type": "literal-union",
                  "literals": ["none", "list", "inline", "both"],
                  "optional": true
                },
                "aria-braillelabel": {
                  "type": "string",
                  "optional": true
                },
                "aria-brailleroledescription": {
                  "type": "string",
                  "optional": true
                },
                "aria-busy": {
                  "type": "Booleanish",
                  "optional": true
                },
                "aria-checked": {
                  "type": "boolean | \"true\" | \"false\" | \"mixed\"",
                  "optional": true
                },
                "aria-colcount": {
                  "type": "number",
                  "optional": true
                },
                "aria-colindex": {
                  "type": "number",
                  "optional": true
                },
                "aria-colindextext": {
                  "type": "string",
                  "optional": true
                },
                "aria-colspan": {
                  "type": "number",
                  "optional": true
                },
                "aria-controls": {
                  "type": "string",
                  "optional": true
                },
                "aria-current": {
                  "type": "boolean | \"time\" | \"true\" | \"false\" | \"page\" | \"step\" | \"location\" | \"date\"",
                  "optional": true
                },
                "aria-describedby": {
                  "type": "string",
                  "optional": true
                },
                "aria-description": {
                  "type": "string",
                  "optional": true
                },
                "aria-details": {
                  "type": "string",
                  "optional": true
                },
                "aria-disabled": {
                  "type": "Booleanish",
                  "optional": true
                },
                "aria-dropeffect": {
                  "type": "literal-union",
                  "literals": [
                    "link",
                    "none",
                    "copy",
                    "execute",
                    "move",
                    "popup"
                  ],
                  "optional": true
                },
                "aria-errormessage": {
                  "type": "string",
                  "optional": true
                },
                "aria-expanded": {
                  "type": "Booleanish",
                  "optional": true
                },
                "aria-flowto": {
                  "type": "string",
                  "optional": true
                },
                "aria-grabbed": {
                  "type": "Booleanish",
                  "optional": true
                },
                "aria-haspopup": {
                  "type": "boolean | \"dialog\" | \"menu\" | \"true\" | \"false\" | \"grid\" | \"listbox\" | \"tree\"",
                  "optional": true
                },
                "aria-hidden": {
                  "type": "Booleanish",
                  "optional": true
                },
                "aria-invalid": {
                  "type": "boolean | \"true\" | \"false\" | \"grammar\" | \"spelling\"",
                  "optional": true
                },
                "aria-keyshortcuts": {
                  "type": "string",
                  "optional": true
                },
                "aria-label": {
                  "type": "string",
                  "optional": true
                },
                "aria-labelledby": {
                  "type": "string",
                  "optional": true
                },
                "aria-level": {
                  "type": "number",
                  "optional": true
                },
                "aria-live": {
                  "type": "literal-union",
                  "literals": ["off", "assertive", "polite"],
                  "optional": true
                },
                "aria-modal": {
                  "type": "Booleanish",
                  "optional": true
                },
                "aria-multiline": {
                  "type": "Booleanish",
                  "optional": true
                },
                "aria-multiselectable": {
                  "type": "Booleanish",
                  "optional": true
                },
                "aria-orientation": {
                  "type": "literal-union",
                  "literals": ["horizontal", "vertical"],
                  "optional": true
                },
                "aria-owns": {
                  "type": "string",
                  "optional": true
                },
                "aria-placeholder": {
                  "type": "string",
                  "optional": true
                },
                "aria-posinset": {
                  "type": "number",
                  "optional": true
                },
                "aria-pressed": {
                  "type": "boolean | \"true\" | \"false\" | \"mixed\"",
                  "optional": true
                },
                "aria-readonly": {
                  "type": "Booleanish",
                  "optional": true
                },
                "aria-relevant": {
                  "type": "\"text\" | \"additions\" | \"additions removals\" | \"additions text\" | \"all\" | \"removals\" | \"removals additions\" | \"removals text\" | \"text additions\" | \"text removals\"",
                  "optional": true
                },
                "aria-required": {
                  "type": "Booleanish",
                  "optional": true
                },
                "aria-roledescription": {
                  "type": "string",
                  "optional": true
                },
                "aria-rowcount": {
                  "type": "number",
                  "optional": true
                },
                "aria-rowindex": {
                  "type": "number",
                  "optional": true
                },
                "aria-rowindextext": {
                  "type": "string",
                  "optional": true
                },
                "aria-rowspan": {
                  "type": "number",
                  "optional": true
                },
                "aria-selected": {
                  "type": "Booleanish",
                  "optional": true
                },
                "aria-setsize": {
                  "type": "number",
                  "optional": true
                },
                "aria-sort": {
                  "type": "literal-union",
                  "literals": ["none", "ascending", "descending", "other"],
                  "optional": true
                },
                "aria-valuemax": {
                  "type": "number",
                  "optional": true
                },
                "aria-valuemin": {
                  "type": "number",
                  "optional": true
                },
                "aria-valuenow": {
                  "type": "number",
                  "optional": true
                },
                "aria-valuetext": {
                  "type": "string",
                  "optional": true
                },
                "dangerouslySetInnerHTML": {
                  "type": "{ __html: string | TrustedHTML; }",
                  "optional": true
                },
                "onCopy": {
                  "type": "React.ClipboardEventHandler<HTMLDivElement> & React.ClipboardEventHandler<HTMLDListElement>",
                  "optional": true
                },
                "onCopyCapture": {
                  "type": "React.ClipboardEventHandler<HTMLDivElement> & React.ClipboardEventHandler<HTMLDListElement>",
                  "optional": true
                },
                "onCut": {
                  "type": "React.ClipboardEventHandler<HTMLDivElement> & React.ClipboardEventHandler<HTMLDListElement>",
                  "optional": true
                },
                "onCutCapture": {
                  "type": "React.ClipboardEventHandler<HTMLDivElement> & React.ClipboardEventHandler<HTMLDListElement>",
                  "optional": true
                },
                "onPaste": {
                  "type": "React.ClipboardEventHandler<HTMLDivElement> & React.ClipboardEventHandler<HTMLDListElement>",
                  "optional": true
                },
                "onPasteCapture": {
                  "type": "React.ClipboardEventHandler<HTMLDivElement> & React.ClipboardEventHandler<HTMLDListElement>",
                  "optional": true
                },
                "onCompositionEnd": {
                  "type": "React.CompositionEventHandler<HTMLDivElement> & React.CompositionEventHandler<HTMLDListElement>",
                  "optional": true
                },
                "onCompositionEndCapture": {
                  "type": "React.CompositionEventHandler<HTMLDivElement> & React.CompositionEventHandler<HTMLDListElement>",
                  "optional": true
                },
                "onCompositionStart": {
                  "type": "React.CompositionEventHandler<HTMLDivElement> & React.CompositionEventHandler<HTMLDListElement>",
                  "optional": true
                },
                "onCompositionStartCapture": {
                  "type": "React.CompositionEventHandler<HTMLDivElement> & React.CompositionEventHandler<HTMLDListElement>",
                  "optional": true
                },
                "onCompositionUpdate": {
                  "type": "React.CompositionEventHandler<HTMLDivElement> & React.CompositionEventHandler<HTMLDListElement>",
                  "optional": true
                },
                "onCompositionUpdateCapture": {
                  "type": "React.CompositionEventHandler<HTMLDivElement> & React.CompositionEventHandler<HTMLDListElement>",
                  "optional": true
                },
                "onFocus": {
                  "type": "React.FocusEventHandler<HTMLDivElement> & React.FocusEventHandler<HTMLDListElement>",
                  "optional": true
                },
                "onFocusCapture": {
                  "type": "React.FocusEventHandler<HTMLDivElement> & React.FocusEventHandler<HTMLDListElement>",
                  "optional": true
                },
                "onBlur": {
                  "type": "React.FocusEventHandler<HTMLDivElement> & React.FocusEventHandler<HTMLDListElement>",
                  "optional": true
                },
                "onBlurCapture": {
                  "type": "React.FocusEventHandler<HTMLDivElement> & React.FocusEventHandler<HTMLDListElement>",
                  "optional": true
                },
                "onChange": {
                  "type": "React.FormEventHandler<HTMLDivElement> & React.FormEventHandler<HTMLDListElement>",
                  "optional": true
                },
                "onChangeCapture": {
                  "type": "React.FormEventHandler<HTMLDivElement> & React.FormEventHandler<HTMLDListElement>",
                  "optional": true
                },
                "onBeforeInput": {
                  "type": "React.InputEventHandler<HTMLDivElement> & React.InputEventHandler<HTMLDListElement>",
                  "optional": true
                },
                "onBeforeInputCapture": {
                  "type": "React.FormEventHandler<HTMLDivElement> & React.FormEventHandler<HTMLDListElement>",
                  "optional": true
                },
                "onInput": {
                  "type": "React.FormEventHandler<HTMLDivElement> & React.FormEventHandler<HTMLDListElement>",
                  "optional": true
                },
                "onInputCapture": {
                  "type": "React.FormEventHandler<HTMLDivElement> & React.FormEventHandler<HTMLDListElement>",
                  "optional": true
                },
                "onReset": {
                  "type": "React.FormEventHandler<HTMLDivElement> & React.FormEventHandler<HTMLDListElement>",
                  "optional": true
                },
                "onResetCapture": {
                  "type": "React.FormEventHandler<HTMLDivElement> & React.FormEventHandler<HTMLDListElement>",
                  "optional": true
                },
                "onSubmit": {
                  "type": "React.FormEventHandler<HTMLDivElement> & React.FormEventHandler<HTMLDListElement>",
                  "optional": true
                },
                "onSubmitCapture": {
                  "type": "React.FormEventHandler<HTMLDivElement> & React.FormEventHandler<HTMLDListElement>",
                  "optional": true
                },
                "onInvalid": {
                  "type": "React.FormEventHandler<HTMLDivElement> & React.FormEventHandler<HTMLDListElement>",
                  "optional": true
                },
                "onInvalidCapture": {
                  "type": "React.FormEventHandler<HTMLDivElement> & React.FormEventHandler<HTMLDListElement>",
                  "optional": true
                },
                "onLoad": {
                  "type": "React.ReactEventHandler<HTMLDivElement> & React.ReactEventHandler<HTMLDListElement>",
                  "optional": true
                },
                "onLoadCapture": {
                  "type": "React.ReactEventHandler<HTMLDivElement> & React.ReactEventHandler<HTMLDListElement>",
                  "optional": true
                },
                "onError": {
                  "type": "React.ReactEventHandler<HTMLDivElement> & React.ReactEventHandler<HTMLDListElement>",
                  "optional": true
                },
                "onErrorCapture": {
                  "type": "React.ReactEventHandler<HTMLDivElement> & React.ReactEventHandler<HTMLDListElement>",
                  "optional": true
                },
                "onKeyDown": {
                  "type": "React.KeyboardEventHandler<HTMLDivElement> & React.KeyboardEventHandler<HTMLDListElement>",
                  "optional": true
                },
                "onKeyDownCapture": {
                  "type": "React.KeyboardEventHandler<HTMLDivElement> & React.KeyboardEventHandler<HTMLDListElement>",
                  "optional": true
                },
                "onKeyPress": {
                  "type": "React.KeyboardEventHandler<HTMLDivElement> & React.KeyboardEventHandler<HTMLDListElement>",
                  "optional": true
                },
                "onKeyPressCapture": {
                  "type": "React.KeyboardEventHandler<HTMLDivElement> & React.KeyboardEventHandler<HTMLDListElement>",
                  "optional": true
                },
                "onKeyUp": {
                  "type": "React.KeyboardEventHandler<HTMLDivElement> & React.KeyboardEventHandler<HTMLDListElement>",
                  "optional": true
                },
                "onKeyUpCapture": {
                  "type": "React.KeyboardEventHandler<HTMLDivElement> & React.KeyboardEventHandler<HTMLDListElement>",
                  "optional": true
                },
                "onAbort": {
                  "type": "React.ReactEventHandler<HTMLDivElement> & React.ReactEventHandler<HTMLDListElement>",
                  "optional": true
                },
                "onAbortCapture": {
                  "type": "React.ReactEventHandler<HTMLDivElement> & React.ReactEventHandler<HTMLDListElement>",
                  "optional": true
                },
                "onCanPlay": {
                  "type": "React.ReactEventHandler<HTMLDivElement> & React.ReactEventHandler<HTMLDListElement>",
                  "optional": true
                },
                "onCanPlayCapture": {
                  "type": "React.ReactEventHandler<HTMLDivElement> & React.ReactEventHandler<HTMLDListElement>",
                  "optional": true
                },
                "onCanPlayThrough": {
                  "type": "React.ReactEventHandler<HTMLDivElement> & React.ReactEventHandler<HTMLDListElement>",
                  "optional": true
                },
                "onCanPlayThroughCapture": {
                  "type": "React.ReactEventHandler<HTMLDivElement> & React.ReactEventHandler<HTMLDListElement>",
                  "optional": true
                },
                "onDurationChange": {
                  "type": "React.ReactEventHandler<HTMLDivElement> & React.ReactEventHandler<HTMLDListElement>",
                  "optional": true
                },
                "onDurationChangeCapture": {
                  "type": "React.ReactEventHandler<HTMLDivElement> & React.ReactEventHandler<HTMLDListElement>",
                  "optional": true
                },
                "onEmptied": {
                  "type": "React.ReactEventHandler<HTMLDivElement> & React.ReactEventHandler<HTMLDListElement>",
                  "optional": true
                },
                "onEmptiedCapture": {
                  "type": "React.ReactEventHandler<HTMLDivElement> & React.ReactEventHandler<HTMLDListElement>",
                  "optional": true
                },
                "onEncrypted": {
                  "type": "React.ReactEventHandler<HTMLDivElement> & React.ReactEventHandler<HTMLDListElement>",
                  "optional": true
                },
                "onEncryptedCapture": {
                  "type": "React.ReactEventHandler<HTMLDivElement> & React.ReactEventHandler<HTMLDListElement>",
                  "optional": true
                },
                "onEnded": {
                  "type": "React.ReactEventHandler<HTMLDivElement> & React.ReactEventHandler<HTMLDListElement>",
                  "optional": true
                },
                "onEndedCapture": {
                  "type": "React.ReactEventHandler<HTMLDivElement> & React.ReactEventHandler<HTMLDListElement>",
                  "optional": true
                },
                "onLoadedData": {
                  "type": "React.ReactEventHandler<HTMLDivElement> & React.ReactEventHandler<HTMLDListElement>",
                  "optional": true
                },
                "onLoadedDataCapture": {
                  "type": "React.ReactEventHandler<HTMLDivElement> & React.ReactEventHandler<HTMLDListElement>",
                  "optional": true
                },
                "onLoadedMetadata": {
                  "type": "React.ReactEventHandler<HTMLDivElement> & React.ReactEventHandler<HTMLDListElement>",
                  "optional": true
                },
                "onLoadedMetadataCapture": {
                  "type": "React.ReactEventHandler<HTMLDivElement> & React.ReactEventHandler<HTMLDListElement>",
                  "optional": true
                },
                "onLoadStart": {
                  "type": "React.ReactEventHandler<HTMLDivElement> & React.ReactEventHandler<HTMLDListElement>",
                  "optional": true
                },
                "onLoadStartCapture": {
                  "type": "React.ReactEventHandler<HTMLDivElement> & React.ReactEventHandler<HTMLDListElement>",
                  "optional": true
                },
                "onPause": {
                  "type": "React.ReactEventHandler<HTMLDivElement> & React.ReactEventHandler<HTMLDListElement>",
                  "optional": true
                },
                "onPauseCapture": {
                  "type": "React.ReactEventHandler<HTMLDivElement> & React.ReactEventHandler<HTMLDListElement>",
                  "optional": true
                },
                "onPlay": {
                  "type": "React.ReactEventHandler<HTMLDivElement> & React.ReactEventHandler<HTMLDListElement>",
                  "optional": true
                },
                "onPlayCapture": {
                  "type": "React.ReactEventHandler<HTMLDivElement> & React.ReactEventHandler<HTMLDListElement>",
                  "optional": true
                },
                "onPlaying": {
                  "type": "React.ReactEventHandler<HTMLDivElement> & React.ReactEventHandler<HTMLDListElement>",
                  "optional": true
                },
                "onPlayingCapture": {
                  "type": "React.ReactEventHandler<HTMLDivElement> & React.ReactEventHandler<HTMLDListElement>",
                  "optional": true
                },
                "onProgress": {
                  "type": "React.ReactEventHandler<HTMLDivElement> & React.ReactEventHandler<HTMLDListElement>",
                  "optional": true
                },
                "onProgressCapture": {
                  "type": "React.ReactEventHandler<HTMLDivElement> & React.ReactEventHandler<HTMLDListElement>",
                  "optional": true
                },
                "onRateChange": {
                  "type": "React.ReactEventHandler<HTMLDivElement> & React.ReactEventHandler<HTMLDListElement>",
                  "optional": true
                },
                "onRateChangeCapture": {
                  "type": "React.ReactEventHandler<HTMLDivElement> & React.ReactEventHandler<HTMLDListElement>",
                  "optional": true
                },
                "onSeeked": {
                  "type": "React.ReactEventHandler<HTMLDivElement> & React.ReactEventHandler<HTMLDListElement>",
                  "optional": true
                },
                "onSeekedCapture": {
                  "type": "React.ReactEventHandler<HTMLDivElement> & React.ReactEventHandler<HTMLDListElement>",
                  "optional": true
                },
                "onSeeking": {
                  "type": "React.ReactEventHandler<HTMLDivElement> & React.ReactEventHandler<HTMLDListElement>",
                  "optional": true
                },
                "onSeekingCapture": {
                  "type": "React.ReactEventHandler<HTMLDivElement> & React.ReactEventHandler<HTMLDListElement>",
                  "optional": true
                },
                "onStalled": {
                  "type": "React.ReactEventHandler<HTMLDivElement> & React.ReactEventHandler<HTMLDListElement>",
                  "optional": true
                },
                "onStalledCapture": {
                  "type": "React.ReactEventHandler<HTMLDivElement> & React.ReactEventHandler<HTMLDListElement>",
                  "optional": true
                },
                "onSuspend": {
                  "type": "React.ReactEventHandler<HTMLDivElement> & React.ReactEventHandler<HTMLDListElement>",
                  "optional": true
                },
                "onSuspendCapture": {
                  "type": "React.ReactEventHandler<HTMLDivElement> & React.ReactEventHandler<HTMLDListElement>",
                  "optional": true
                },
                "onTimeUpdate": {
                  "type": "React.ReactEventHandler<HTMLDivElement> & React.ReactEventHandler<HTMLDListElement>",
                  "optional": true
                },
                "onTimeUpdateCapture": {
                  "type": "React.ReactEventHandler<HTMLDivElement> & React.ReactEventHandler<HTMLDListElement>",
                  "optional": true
                },
                "onVolumeChange": {
                  "type": "React.ReactEventHandler<HTMLDivElement> & React.ReactEventHandler<HTMLDListElement>",
                  "optional": true
                },
                "onVolumeChangeCapture": {
                  "type": "React.ReactEventHandler<HTMLDivElement> & React.ReactEventHandler<HTMLDListElement>",
                  "optional": true
                },
                "onWaiting": {
                  "type": "React.ReactEventHandler<HTMLDivElement> & React.ReactEventHandler<HTMLDListElement>",
                  "optional": true
                },
                "onWaitingCapture": {
                  "type": "React.ReactEventHandler<HTMLDivElement> & React.ReactEventHandler<HTMLDListElement>",
                  "optional": true
                },
                "onAuxClick": {
                  "type": "React.MouseEventHandler<HTMLDivElement> & React.MouseEventHandler<HTMLDListElement>",
                  "optional": true
                },
                "onAuxClickCapture": {
                  "type": "React.MouseEventHandler<HTMLDivElement> & React.MouseEventHandler<HTMLDListElement>",
                  "optional": true
                },
                "onClick": {
                  "type": "React.MouseEventHandler<HTMLDivElement> & React.MouseEventHandler<HTMLDListElement>",
                  "optional": true
                },
                "onClickCapture": {
                  "type": "React.MouseEventHandler<HTMLDivElement> & React.MouseEventHandler<HTMLDListElement>",
                  "optional": true
                },
                "onContextMenu": {
                  "type": "React.MouseEventHandler<HTMLDivElement> & React.MouseEventHandler<HTMLDListElement>",
                  "optional": true
                },
                "onContextMenuCapture": {
                  "type": "React.MouseEventHandler<HTMLDivElement> & React.MouseEventHandler<HTMLDListElement>",
                  "optional": true
                },
                "onDoubleClick": {
                  "type": "React.MouseEventHandler<HTMLDivElement> & React.MouseEventHandler<HTMLDListElement>",
                  "optional": true
                },
                "onDoubleClickCapture": {
                  "type": "React.MouseEventHandler<HTMLDivElement> & React.MouseEventHandler<HTMLDListElement>",
                  "optional": true
                },
                "onDrag": {
                  "type": "React.DragEventHandler<HTMLDivElement> & React.DragEventHandler<HTMLDListElement>",
                  "optional": true
                },
                "onDragCapture": {
                  "type": "React.DragEventHandler<HTMLDivElement> & React.DragEventHandler<HTMLDListElement>",
                  "optional": true
                },
                "onDragEnd": {
                  "type": "React.DragEventHandler<HTMLDivElement> & React.DragEventHandler<HTMLDListElement>",
                  "optional": true
                },
                "onDragEndCapture": {
                  "type": "React.DragEventHandler<HTMLDivElement> & React.DragEventHandler<HTMLDListElement>",
                  "optional": true
                },
                "onDragEnter": {
                  "type": "React.DragEventHandler<HTMLDivElement> & React.DragEventHandler<HTMLDListElement>",
                  "optional": true
                },
                "onDragEnterCapture": {
                  "type": "React.DragEventHandler<HTMLDivElement> & React.DragEventHandler<HTMLDListElement>",
                  "optional": true
                },
                "onDragExit": {
                  "type": "React.DragEventHandler<HTMLDivElement> & React.DragEventHandler<HTMLDListElement>",
                  "optional": true
                },
                "onDragExitCapture": {
                  "type": "React.DragEventHandler<HTMLDivElement> & React.DragEventHandler<HTMLDListElement>",
                  "optional": true
                },
                "onDragLeave": {
                  "type": "React.DragEventHandler<HTMLDivElement> & React.DragEventHandler<HTMLDListElement>",
                  "optional": true
                },
                "onDragLeaveCapture": {
                  "type": "React.DragEventHandler<HTMLDivElement> & React.DragEventHandler<HTMLDListElement>",
                  "optional": true
                },
                "onDragOver": {
                  "type": "React.DragEventHandler<HTMLDivElement> & React.DragEventHandler<HTMLDListElement>",
                  "optional": true
                },
                "onDragOverCapture": {
                  "type": "React.DragEventHandler<HTMLDivElement> & React.DragEventHandler<HTMLDListElement>",
                  "optional": true
                },
                "onDragStart": {
                  "type": "React.DragEventHandler<HTMLDivElement> & React.DragEventHandler<HTMLDListElement>",
                  "optional": true
                },
                "onDragStartCapture": {
                  "type": "React.DragEventHandler<HTMLDivElement> & React.DragEventHandler<HTMLDListElement>",
                  "optional": true
                },
                "onDrop": {
                  "type": "React.DragEventHandler<HTMLDivElement> & React.DragEventHandler<HTMLDListElement>",
                  "optional": true
                },
                "onDropCapture": {
                  "type": "React.DragEventHandler<HTMLDivElement> & React.DragEventHandler<HTMLDListElement>",
                  "optional": true
                },
                "onMouseDown": {
                  "type": "React.MouseEventHandler<HTMLDivElement> & React.MouseEventHandler<HTMLDListElement>",
                  "optional": true
                },
                "onMouseDownCapture": {
                  "type": "React.MouseEventHandler<HTMLDivElement> & React.MouseEventHandler<HTMLDListElement>",
                  "optional": true
                },
                "onMouseEnter": {
                  "type": "React.MouseEventHandler<HTMLDivElement> & React.MouseEventHandler<HTMLDListElement>",
                  "optional": true
                },
                "onMouseLeave": {
                  "type": "React.MouseEventHandler<HTMLDivElement> & React.MouseEventHandler<HTMLDListElement>",
                  "optional": true
                },
                "onMouseMove": {
                  "type": "React.MouseEventHandler<HTMLDivElement> & React.MouseEventHandler<HTMLDListElement>",
                  "optional": true
                },
                "onMouseMoveCapture": {
                  "type": "React.MouseEventHandler<HTMLDivElement> & React.MouseEventHandler<HTMLDListElement>",
                  "optional": true
                },
                "onMouseOut": {
                  "type": "React.MouseEventHandler<HTMLDivElement> & React.MouseEventHandler<HTMLDListElement>",
                  "optional": true
                },
                "onMouseOutCapture": {
                  "type": "React.MouseEventHandler<HTMLDivElement> & React.MouseEventHandler<HTMLDListElement>",
                  "optional": true
                },
                "onMouseOver": {
                  "type": "React.MouseEventHandler<HTMLDivElement> & React.MouseEventHandler<HTMLDListElement>",
                  "optional": true
                },
                "onMouseOverCapture": {
                  "type": "React.MouseEventHandler<HTMLDivElement> & React.MouseEventHandler<HTMLDListElement>",
                  "optional": true
                },
                "onMouseUp": {
                  "type": "React.MouseEventHandler<HTMLDivElement> & React.MouseEventHandler<HTMLDListElement>",
                  "optional": true
                },
                "onMouseUpCapture": {
                  "type": "React.MouseEventHandler<HTMLDivElement> & React.MouseEventHandler<HTMLDListElement>",
                  "optional": true
                },
                "onSelect": {
                  "type": "React.ReactEventHandler<HTMLDivElement> & React.ReactEventHandler<HTMLDListElement>",
                  "optional": true
                },
                "onSelectCapture": {
                  "type": "React.ReactEventHandler<HTMLDivElement> & React.ReactEventHandler<HTMLDListElement>",
                  "optional": true
                },
                "onTouchCancel": {
                  "type": "React.TouchEventHandler<HTMLDivElement> & React.TouchEventHandler<HTMLDListElement>",
                  "optional": true
                },
                "onTouchCancelCapture": {
                  "type": "React.TouchEventHandler<HTMLDivElement> & React.TouchEventHandler<HTMLDListElement>",
                  "optional": true
                },
                "onTouchEnd": {
                  "type": "React.TouchEventHandler<HTMLDivElement> & React.TouchEventHandler<HTMLDListElement>",
                  "optional": true
                },
                "onTouchEndCapture": {
                  "type": "React.TouchEventHandler<HTMLDivElement> & React.TouchEventHandler<HTMLDListElement>",
                  "optional": true
                },
                "onTouchMove": {
                  "type": "React.TouchEventHandler<HTMLDivElement> & React.TouchEventHandler<HTMLDListElement>",
                  "optional": true
                },
                "onTouchMoveCapture": {
                  "type": "React.TouchEventHandler<HTMLDivElement> & React.TouchEventHandler<HTMLDListElement>",
                  "optional": true
                },
                "onTouchStart": {
                  "type": "React.TouchEventHandler<HTMLDivElement> & React.TouchEventHandler<HTMLDListElement>",
                  "optional": true
                },
                "onTouchStartCapture": {
                  "type": "React.TouchEventHandler<HTMLDivElement> & React.TouchEventHandler<HTMLDListElement>",
                  "optional": true
                },
                "onPointerDown": {
                  "type": "React.PointerEventHandler<HTMLDivElement> & React.PointerEventHandler<HTMLDListElement>",
                  "optional": true
                },
                "onPointerDownCapture": {
                  "type": "React.PointerEventHandler<HTMLDivElement> & React.PointerEventHandler<HTMLDListElement>",
                  "optional": true
                },
                "onPointerMove": {
                  "type": "React.PointerEventHandler<HTMLDivElement> & React.PointerEventHandler<HTMLDListElement>",
                  "optional": true
                },
                "onPointerMoveCapture": {
                  "type": "React.PointerEventHandler<HTMLDivElement> & React.PointerEventHandler<HTMLDListElement>",
                  "optional": true
                },
                "onPointerUp": {
                  "type": "React.PointerEventHandler<HTMLDivElement> & React.PointerEventHandler<HTMLDListElement>",
                  "optional": true
                },
                "onPointerUpCapture": {
                  "type": "React.PointerEventHandler<HTMLDivElement> & React.PointerEventHandler<HTMLDListElement>",
                  "optional": true
                },
                "onPointerCancel": {
                  "type": "React.PointerEventHandler<HTMLDivElement> & React.PointerEventHandler<HTMLDListElement>",
                  "optional": true
                },
                "onPointerCancelCapture": {
                  "type": "React.PointerEventHandler<HTMLDivElement> & React.PointerEventHandler<HTMLDListElement>",
                  "optional": true
                },
                "onPointerEnter": {
                  "type": "React.PointerEventHandler<HTMLDivElement> & React.PointerEventHandler<HTMLDListElement>",
                  "optional": true
                },
                "onPointerLeave": {
                  "type": "React.PointerEventHandler<HTMLDivElement> & React.PointerEventHandler<HTMLDListElement>",
                  "optional": true
                },
                "onPointerOver": {
                  "type": "React.PointerEventHandler<HTMLDivElement> & React.PointerEventHandler<HTMLDListElement>",
                  "optional": true
                },
                "onPointerOverCapture": {
                  "type": "React.PointerEventHandler<HTMLDivElement> & React.PointerEventHandler<HTMLDListElement>",
                  "optional": true
                },
                "onPointerOut": {
                  "type": "React.PointerEventHandler<HTMLDivElement> & React.PointerEventHandler<HTMLDListElement>",
                  "optional": true
                },
                "onPointerOutCapture": {
                  "type": "React.PointerEventHandler<HTMLDivElement> & React.PointerEventHandler<HTMLDListElement>",
                  "optional": true
                },
                "onGotPointerCapture": {
                  "type": "React.PointerEventHandler<HTMLDivElement> & React.PointerEventHandler<HTMLDListElement>",
                  "optional": true
                },
                "onGotPointerCaptureCapture": {
                  "type": "React.PointerEventHandler<HTMLDivElement> & React.PointerEventHandler<HTMLDListElement>",
                  "optional": true
                },
                "onLostPointerCapture": {
                  "type": "React.PointerEventHandler<HTMLDivElement> & React.PointerEventHandler<HTMLDListElement>",
                  "optional": true
                },
                "onLostPointerCaptureCapture": {
                  "type": "React.PointerEventHandler<HTMLDivElement> & React.PointerEventHandler<HTMLDListElement>",
                  "optional": true
                },
                "onScroll": {
                  "type": "React.UIEventHandler<HTMLDivElement> & React.UIEventHandler<HTMLDListElement>",
                  "optional": true
                },
                "onScrollCapture": {
                  "type": "React.UIEventHandler<HTMLDivElement> & React.UIEventHandler<HTMLDListElement>",
                  "optional": true
                },
                "onScrollEnd": {
                  "type": "React.UIEventHandler<HTMLDivElement> & React.UIEventHandler<HTMLDListElement>",
                  "optional": true
                },
                "onScrollEndCapture": {
                  "type": "React.UIEventHandler<HTMLDivElement> & React.UIEventHandler<HTMLDListElement>",
                  "optional": true
                },
                "onWheel": {
                  "type": "React.WheelEventHandler<HTMLDivElement> & React.WheelEventHandler<HTMLDListElement>",
                  "optional": true
                },
                "onWheelCapture": {
                  "type": "React.WheelEventHandler<HTMLDivElement> & React.WheelEventHandler<HTMLDListElement>",
                  "optional": true
                },
                "onAnimationStart": {
                  "type": "React.AnimationEventHandler<HTMLDivElement> & React.AnimationEventHandler<HTMLDListElement>",
                  "optional": true
                },
                "onAnimationStartCapture": {
                  "type": "React.AnimationEventHandler<HTMLDivElement> & React.AnimationEventHandler<HTMLDListElement>",
                  "optional": true
                },
                "onAnimationEnd": {
                  "type": "React.AnimationEventHandler<HTMLDivElement> & React.AnimationEventHandler<HTMLDListElement>",
                  "optional": true
                },
                "onAnimationEndCapture": {
                  "type": "React.AnimationEventHandler<HTMLDivElement> & React.AnimationEventHandler<HTMLDListElement>",
                  "optional": true
                },
                "onAnimationIteration": {
                  "type": "React.AnimationEventHandler<HTMLDivElement> & React.AnimationEventHandler<HTMLDListElement>",
                  "optional": true
                },
                "onAnimationIterationCapture": {
                  "type": "React.AnimationEventHandler<HTMLDivElement> & React.AnimationEventHandler<HTMLDListElement>",
                  "optional": true
                },
                "onToggle": {
                  "type": "React.ToggleEventHandler<HTMLDivElement> & React.ToggleEventHandler<HTMLDListElement>",
                  "optional": true
                },
                "onBeforeToggle": {
                  "type": "React.ToggleEventHandler<HTMLDivElement> & React.ToggleEventHandler<HTMLDListElement>",
                  "optional": true
                },
                "onTransitionCancel": {
                  "type": "React.TransitionEventHandler<HTMLDivElement> & React.TransitionEventHandler<HTMLDListElement>",
                  "optional": true
                },
                "onTransitionCancelCapture": {
                  "type": "React.TransitionEventHandler<HTMLDivElement> & React.TransitionEventHandler<HTMLDListElement>",
                  "optional": true
                },
                "onTransitionEnd": {
                  "type": "React.TransitionEventHandler<HTMLDivElement> & React.TransitionEventHandler<HTMLDListElement>",
                  "optional": true
                },
                "onTransitionEndCapture": {
                  "type": "React.TransitionEventHandler<HTMLDivElement> & React.TransitionEventHandler<HTMLDListElement>",
                  "optional": true
                },
                "onTransitionRun": {
                  "type": "React.TransitionEventHandler<HTMLDivElement> & React.TransitionEventHandler<HTMLDListElement>",
                  "optional": true
                },
                "onTransitionRunCapture": {
                  "type": "React.TransitionEventHandler<HTMLDivElement> & React.TransitionEventHandler<HTMLDListElement>",
                  "optional": true
                },
                "onTransitionStart": {
                  "type": "React.TransitionEventHandler<HTMLDivElement> & React.TransitionEventHandler<HTMLDListElement>",
                  "optional": true
                },
                "onTransitionStartCapture": {
                  "type": "React.TransitionEventHandler<HTMLDivElement> & React.TransitionEventHandler<HTMLDListElement>",
                  "optional": true
                },
                "isLoading": {
                  "type": "boolean",
                  "optional": true
                },
                "header": "string",
                "subheader": "string",
                "classNames": {
                  "type": "{ list?: string; label?: string; value?: string; }",
                  "optional": true
                },
                "align": {
                  "type": "literal-union",
                  "literals": ["center", "justify", "left"],
                  "optional": true
                }
              },
              "emits": {}
            },
            "semanticHash": "uif:f292a3d265a1d560c7047f28",
            "fileHash": "uif:5597bba2742ed8d8ce3e34eb"
          },
          "codeHeader": null,
          "code": "/*\n * Copyright 2025 Hypergiant Galactic Systems Inc. All rights reserved.\n * This file is licensed to you under the Apache License, Version 2.0 (the \"License\");\n * you may not use this file except in compliance with the License. You may obtain a copy\n * of the License at https://www.apache.org/licenses/LICENSE-2.0\n *\n * Unless required by applicable law or agreed to in writing, software distributed under\n * the License is distributed on an \"AS IS\" BASIS, WITHOUT WARRANTIES OR REPRESENTATIONS\n * OF ANY KIND, either express or implied. See the License for the specific language\n * governing permissions and limitations under the License.\n */\n\nimport type { ComponentPropsWithRef, PropsWithChildren } from 'react';\nimport type { DetailsListProps } from '../details-list/types';\n\nexport type FlashcardComponentProps = PropsWithChildren &\n  ComponentPropsWithRef<'div'>;\n\nexport type FlashcardProps = FlashcardComponentProps & {\n  isLoading?: boolean;\n  header: string;\n  subheader: string;\n};\n\nexport type FlashcardDetailsListProps = FlashcardComponentProps &\n  Partial<DetailsListProps>;\n"
        }
      ],
      "edges": []
    },
    "meta": {
      "missing": [],
      "source": "logicstamp-context@0.3.2"
    }
  }
]
